lavender_pinyin/__init__.py
lavender_pinyin/dictionary.py
lavender_pinyin/dictionaries/bopomofo/dictionary.json
lavender_pinyin/dictionaries/bopomofo_first/dictionary.json
lavender_pinyin/dictionaries/finals/dictionary.json
lavender_pinyin/dictionaries/finals_tone/dictionary.json
lavender_pinyin/dictionaries/finals_tone2/dictionary.json
lavender_pinyin/dictionaries/finals_tone3/dictionary.json
lavender_pinyin/dictionaries/initials/dictionary.json
lavender_pinyin/dictionaries/normal/dictionary.json
lavender_pinyin/dictionaries/tone/dictionary.json
lavender_pinyin/dictionaries/tone2/dictionary.json
lavender_pinyin/dictionaries/tone3/dictionary.json
lavender_pinyin-0.0.3.dist-info/licenses/LICENSE
lavender_pinyin-0.0.3.dist-info/METADATA
lavender_pinyin-0.0.3.dist-info/WHEEL
lavender_pinyin-0.0.3.dist-info/top_level.txt
lavender_pinyin-0.0.3.dist-info/RECORD
